text2me/__init__.py
Text2Me-0.0.1.dist-info/LICENSE
Text2Me-0.0.1.dist-info/METADATA
Text2Me-0.0.1.dist-info/WHEEL
Text2Me-0.0.1.dist-info/top_level.txt
Text2Me-0.0.1.dist-info/RECORD
