Metadata-Version: 2.1
Name: Text2Me
Version: 0.0.1
Summary: text2me ——通过Twilio发消息给自己手机
Home-page: https://github.com/CHUA-X/Text2Me
Author: CHUA某人
Author-email: CHUA某人 <chua-x@outlook.com>
Project-URL: Homepage, https://github.com/CHUA-X/Text2Me
Project-URL: Bug Tracker, https://github.com/CHUA-X/Text2Me/issues
Classifier: Development Status :: 3 - Alpha
Classifier: Programming Language :: Python
Classifier: Programming Language :: Python :: 3
Classifier: Programming Language :: Python :: 3 :: Only
Classifier: License :: OSI Approved :: MIT License
Classifier: Natural Language :: Chinese (Simplified)
Classifier: Natural Language :: English
Classifier: Operating System :: Unix
Classifier: Operating System :: POSIX :: Linux
Classifier: Operating System :: MacOS :: MacOS X
Classifier: Operating System :: Microsoft :: Windows
Requires-Python: >=3.6
License-File: LICENSE
